tulyp/__init__.py
tulyp/config/__init__.py
tulyp/config/constants.py
tulyp/exceptions/__init__.py
tulyp/exceptions/lyrics_not_found.py
tulyp/lyrics_sources/__init__.py
tulyp/lyrics_sources/azlyrics.py
tulyp/lyrics_sources/genius.py
tulyp/lyrics_sources/google.py
tulyp/screen/__init__.py
tulyp/screen/ui.py
tulyp/utils/__init__.py
tulyp/utils/misc.py
tulyp-0.1.1.dist-info/METADATA
tulyp-0.1.1.dist-info/WHEEL
tulyp-0.1.1.dist-info/entry_points.txt
tulyp-0.1.1.dist-info/licenses/LICENSE
tulyp-0.1.1.dist-info/RECORD
