Metadata-Version: 2.3
Name: tulyp
Version: 0.1.1
Summary: Display lyrics of the currently playing song in a terminal.
Project-URL: Homepage, https://github.com/laszloszurok/tulyp
Project-URL: Bug Tracker, https://github.com/laszloszurok/tulyp/issues
Author-email: pulzar <pulzar@envs.net>
License-File: LICENSE
Classifier: License :: OSI Approved :: MIT License
Classifier: Operating System :: OS Independent
Classifier: Programming Language :: Python :: 3
Requires-Python: >=3.10
Requires-Dist: beautifulsoup4
Requires-Dist: dbus-python
Requires-Dist: lyricsgenius
Requires-Dist: psutil
Requires-Dist: requests
